IPRadar2/CheckableComboBox.py
IPRadar2/IPRadar2.py
IPRadar2/Ui_mainWindow.py
IPRadar2/__init__.py
IPRadar2/badConnectionKiller.py
IPRadar2/configuration.py
IPRadar2/firewallManager.py
IPRadar2/helper_functions.py
IPRadar2/hostResolver.py
IPRadar2/init_app.py
IPRadar2/mainAppWindow.py
IPRadar2/node.py
IPRadar2/pingResolver.py
IPRadar2/processor.py
IPRadar2/pysharkSniffer.py
IPRadar2/updateRequirements.py
IPRadar2/Config/config.ini
IPRadar2/Config/locationsResolved.json
IPRadar2/Icons/marker-dot-icon.png
IPRadar2/Icons/marker-icon.png
IPRadar2/img/app1.jpg
IPRadar2/img/app2.jpg
ipradar2-0.0.9.data/data/README.md
ipradar2-0.0.9.data/data/Config/config.ini
ipradar2-0.0.9.data/data/Config/locationsResolved.json
ipradar2-0.0.9.data/data/Icons/marker-dot-icon.png
ipradar2-0.0.9.data/data/Icons/marker-icon.png
ipradar2-0.0.9.data/data/img/app1.jpg
ipradar2-0.0.9.data/data/img/app2.jpg
ipradar2-0.0.9.dist-info/LICENSE
ipradar2-0.0.9.dist-info/METADATA
ipradar2-0.0.9.dist-info/WHEEL
ipradar2-0.0.9.dist-info/dependency_links.txt
ipradar2-0.0.9.dist-info/entry_points.txt
ipradar2-0.0.9.dist-info/top_level.txt
ipradar2-0.0.9.dist-info/RECORD
