Metadata-Version: 2.1
Name: ipradar2
Version: 0.0.9
Summary: Intrusion Detection and Prevention in real time based e.g. on geographical locations of hosts
Home-page: https://www.codeproject.com/Articles/5269206/IP-Radar-2-Real-Time-Detection-and-Defense
Author: Clark Fieseln
Author-email: 
License: MIT
Project-URL: Source, https://github.com/ClarkFieseln/IPRadar2ForLinux
Keywords: cybersecurity,cyber security,cyber-security,security,IDS,IDPS,NW-IDS,NW IDS,network IDS,network-IDS,pyqt5,open streetmap,open-streetmap,network-analysis,firewall,pyshark,tshark,pyqt
Classifier: License :: OSI Approved :: MIT License
Classifier: Programming Language :: Python :: 3.7
Classifier: Programming Language :: Python :: 3.8
Classifier: Programming Language :: Python :: 3.9
Classifier: Programming Language :: Python :: 3.10
Classifier: Development Status :: 5 - Production/Stable
Classifier: Environment :: X11 Applications :: Qt
Classifier: Intended Audience :: End Users/Desktop
Classifier: Intended Audience :: Developers
Classifier: Operating System :: POSIX :: Linux
Classifier: Topic :: Security
License-File: LICENSE
Requires-Dist: getmac >=0.8.2
Requires-Dist: ip2geotools >=0.1.6
Requires-Dist: playsound ~=1.2.2
Requires-Dist: psutil >=5.9.8
Requires-Dist: pycountry >=19.8.18
Requires-Dist: PyQt5 >=5.15.10
Requires-Dist: pyshark >=0.6
Requires-Dist: pythonping >=1.0.8
Requires-Dist: Requests ~=2.31.0
Requires-Dist: folium >=0.15.1
Requires-Dist: geographiclib >=2.0
